spice2agm/__init__.py
spice2agm/spice2agm.py
spice2agm-1.2.1.dist-info/METADATA
spice2agm-1.2.1.dist-info/WHEEL
spice2agm-1.2.1.dist-info/entry_points.txt
spice2agm-1.2.1.dist-info/top_level.txt
spice2agm-1.2.1.dist-info/RECORD
