Metadata-Version: 2.1
Name: spice2agm
Version: 1.2.1
Summary: Generator of AGM XML files from SPICE frames and directions
Home-page: https://juigitlab.esac.esa.int/core-system/uplink/spice2agm
Author: JUICE SOC team
Author-email: juice_soc@cosmos.esa.int
Keywords: esa,Juice
Classifier: Development Status :: 4 - Beta
Classifier: Intended Audience :: Science/Research
Classifier: Topic :: Scientific/Engineering :: Astronomy
Classifier: Programming Language :: Python :: 3.9
Requires-Dist: build
Requires-Dist: lxml
Requires-Dist: numpy
Requires-Dist: sphinx
Requires-Dist: sphinx-argparse
Requires-Dist: spiceypy
Requires-Dist: python-dotenv
